Workbook
Name A1_Empresa: Empresas_[Nombre Empresa]
Name A2_Bancos: Listas!$A$2:$A$23
Name A3_Documento: Listas!$B$2:$B$6

Sheet Formulario
B1: N° Operación | E1: Formulario de Rendición de Caja chica, Fondos por rendir, Reembolso de gastos 2026 | Z1: Cuenta no usa concepto
Z2: Centro no usa partida
B3: N° Req.
B5: * Uso exclusivo Control Pagos
A7: Tipo de rendición
A11: FALSE | D11: FALSE | H11: FALSE | J11: Número de Fondo por rendir
A13: Información del responsable
A15: Nombre Responsable | J15: Rut
A17: Cargo | J17: Teléfono / Cel
A19: Empresa | J19: Fecha
A22: Tipo de Cuenta | G22: N° Cuenta | J22: Banco
A24: Información de la rendición
A27: Tipo de Doc. | B27: Fecha | C27: N° Doc | D27: Descripción | H27: Centro de Responsabilidad | I27: Cuenta Contable | J27: Partida | L27: Clasificación | M27: Monto ($)
N28: =A28&"|"&I28&"|"&J28&"|"&L28 | Z28: =+VLOOKUP(H28,'2. Centros'!J:K,2,0)
N29: =A29&"|"&I29&"|"&J29&"|"&L29 | Z29: =+VLOOKUP(H29,'2. Centros'!J:K,2,0)
N30: =A30&"|"&I30&"|"&J30&"|"&L30 | Z30: =+VLOOKUP(H30,'2. Centros'!J:K,2,0)
N31: =A31&"|"&I31&"|"&J31&"|"&L31 | Z31: =+VLOOKUP(H31,'2. Centros'!J:K,2,0)
N32: =A32&"|"&I32&"|"&J32&"|"&L32 | Z32: =+VLOOKUP(H32,'2. Centros'!J:K,2,0)
N33: =A33&"|"&I33&"|"&J33&"|"&L33 | Z33: =+VLOOKUP(H33,'2. Centros'!J:K,2,0)
N34: =A34&"|"&I34&"|"&J34&"|"&L34 | Z34: =+VLOOKUP(H34,'2. Centros'!J:K,2,0)
N35: =A35&"|"&I35&"|"&J35&"|"&L35 | Z35: =+VLOOKUP(H35,'2. Centros'!J:K,2,0)
N36: =A36&"|"&I36&"|"&J36&"|"&L36 | Z36: =+VLOOKUP(H36,'2. Centros'!J:K,2,0)
N37: =A37&"|"&I37&"|"&J37&"|"&L37 | Z37: =+VLOOKUP(H37,'2. Centros'!J:K,2,0)
N38: =A38&"|"&I38&"|"&J38&"|"&L38 | Z38: =+VLOOKUP(H38,'2. Centros'!J:K,2,0)
N39: =A39&"|"&I39&"|"&J39&"|"&L39 | Z39: =+VLOOKUP(H39,'2. Centros'!J:K,2,0)
... N42: =A42&"|"&I42&"|"&J42&"|"&L42 | Z42: =+VLOOKUP(H42,'2. Centros'!J:K,2,0)
H43: Total | M43: =SUM(M28:M41,M58:M85) | Z43: =+VLOOKUP(H43,'2. Centros'!J:K,2,0)
H44: (-) Anticipos | Z44: =+VLOOKUP(H44,'2. Centros'!J:K,2,0)
H45: Total Boletas y Facturas | M45: =+M43+M44 | Z45: =+VLOOKUP(H45,'2. Centros'!J:K,2,0)
Z46: =+VLOOKUP(H46,'2. Centros'!J:K,2,0)
Z47: =+VLOOKUP(H47,'2. Centros'!J:K,2,0)
B48: Firma Responsable del Fondo o Caja | H48: Firma Aprobador | L48: Firma Control Pagos | Z48: =+VLOOKUP(H48,'2. Centros'!J:K,2,0)
E49: Formulario de Rendición de Caja chica, Fondos por rendir, Reembolso de gastos 2026 (Hoja 2) | Z49: =+VLOOKUP(H49,'2. Centros'!J:K,2,0)
Z50: =+VLOOKUP(H50,'2. Centros'!J:K,2,0)
Z51: =+VLOOKUP(H51,'2. Centros'!J:K,2,0)
Z52: =+VLOOKUP(H52,'2. Centros'!J:K,2,0)
Z53: =+VLOOKUP(H53,'2. Centros'!J:K,2,0)
Z54: =+VLOOKUP(H54,'2. Centros'!J:K,2,0)
Z55: =+VLOOKUP(H55,'2. Centros'!J:K,2,0)
Z56: =+VLOOKUP(H56,'2. Centros'!J:K,2,0)
A57: Tipo de Doc. | B57: Fecha | C57: N° Doc | D57: Detalle | H57: Centro de Responsabilidad | I57: Cuenta Contable | J57: Partida | L57: Clasificación | M57: Monto ($) | Z57: =+VLOOKUP(H57,'2. Centros'!J:K,2,0)
N58: =A58&"|"&I58&"|"&J58&"|"&L58 | Z58: =+VLOOKUP(H58,'2. Centros'!J:K,2,0)
N59: =A59&"|"&I59&"|"&J59&"|"&L59 | Z59: =+VLOOKUP(H59,'2. Centros'!J:K,2,0)
N60: =A60&"|"&I60&"|"&J60&"|"&L60 | Z60: =+VLOOKUP(H60,'2. Centros'!J:K,2,0)
N61: =A61&"|"&I61&"|"&J61&"|"&L61 | Z61: =+VLOOKUP(H61,'2. Centros'!J:K,2,0)
N62: =A62&"|"&I62&"|"&J62&"|"&L62 | Z62: =+VLOOKUP(H62,'2. Centros'!J:K,2,0)
N63: =A63&"|"&I63&"|"&J63&"|"&L63 | Z63: =+VLOOKUP(H63,'2. Centros'!J:K,2,0)
N64: =A64&"|"&I64&"|"&J64&"|"&L64 | Z64: =+VLOOKUP(H64,'2. Centros'!J:K,2,0)
N65: =A65&"|"&I65&"|"&J65&"|"&L65 | Z65: =+VLOOKUP(H65,'2. Centros'!J:K,2,0)
N66: =A66&"|"&I66&"|"&J66&"|"&L66 | Z66: =+VLOOKUP(H66,'2. Centros'!J:K,2,0)
N67: =A67&"|"&I67&"|"&J67&"|"&L67 | Z67: =+VLOOKUP(H67,'2. Centros'!J:K,2,0)
N68: =A68&"|"&I68&"|"&J68&"|"&L68 | Z68: =+VLOOKUP(H68,'2. Centros'!J:K,2,0)
N69: =A69&"|"&I69&"|"&J69&"|"&L69 | Z69: =+VLOOKUP(H69,'2. Centros'!J:K,2,0)
... N85: =A85&"|"&I85&"|"&J85&"|"&L85 | Z85: =+VLOOKUP(H85,'2. Centros'!J:K,2,0)
H86: Resumen
H88: Tipo | I88: Cuenta | J88: Partida | L88: Clasificación | M88: Monto
H89: =IFERROR(LEFT($O89,SEARCH("|",$O89)-1),"") | I89: =IFERROR(MID($O89,SEARCH("|",$O89)+1,SEARCH("|",$O89,SEARCH("|",$O89)+1)-SEARCH("|",$O89)-1),"") | J89: =IFERROR(MID($O89,SEARCH("|",$O89,SEARCH("|",$O89)+1)+1,SEARCH("|",$O89,SEARCH("|",$O89,SEARCH("|",$O89)+1)+1)-SEARCH("|",$O89,SEARCH("|",$O89)+1)-1),"") | L89: =IFERROR(RIGHT($O89,LEN($O89)-SEARCH("|",$O89,SEARCH("|",$O89,SEARCH("|",$O89)+1)+1)),"") | M89: =+IF(SUMIFS(Formulario!$M$28:$M$41,Formulario!$A$28:$A$41,$H89,Formulario!$I$28:$I$41,$I89,Formulario!$J$28:$J$41,$J89,Formulario!$L$28:$L$41,$L89)+SUMIFS(Formulario!$M$58:$M$85,Formulario!$A$58:$A$85,$H89,Formulario!$I$58:$I$85,$I89,Formulario!$J$58:$J$85,$J89,Formulario!$L$58:$L$85,$L89)=0,"",SUMIFS(Formulario!$M$28:$M$41,Formulario!$A$28:$A$41,$H89,Formulario!$I$28:$I$41,$I89,Formulario!$J$28:$J$41,$J89,Formulario!$L$28:$L$41,$L89)+SUMIFS(Formulario!$M$58:$M$85,Formulario!$A$58:$A$85,$H89,Formulario!$I$58:$I$85,$I89,Formulario!$J$58:$J$85,$J89,Formulario!$L$58:$L$85,$L89)) | O89: {=IFERROR(INDEX(Formulario!$N$28:$N$85,MATCH(0,COUNTIF($O$88:O88,Formulario!$N$28:$N$85),0)),"")}
H90: =IFERROR(LEFT($O90,SEARCH("|",$O90)-1),"") | I90: =IFERROR(MID($O90,SEARCH("|",$O90)+1,SEARCH("|",$O90,SEARCH("|",$O90)+1)-SEARCH("|",$O90)-1),"") | J90: =IFERROR(MID($O90,SEARCH("|",$O90,SEARCH("|",$O90)+1)+1,SEARCH("|",$O90,SEARCH("|",$O90,SEARCH("|",$O90)+1)+1)-SEARCH("|",$O90,SEARCH("|",$O90)+1)-1),"") | L90: =IFERROR(RIGHT($O90,LEN($O90)-SEARCH("|",$O90,SEARCH("|",$O90,SEARCH("|",$O90)+1)+1)),"") | M90: =+IF(SUMIFS(Formulario!$M$28:$M$41,Formulario!$A$28:$A$41,$H90,Formulario!$I$28:$I$41,$I90,Formulario!$J$28:$J$41,$J90,Formulario!$L$28:$L$41,$L90)+SUMIFS(Formulario!$M$58:$M$85,Formulario!$A$58:$A$85,$H90,Formulario!$I$58:$I$85,$I90,Formulario!$J$58:$J$85,$J90,Formulario!$L$58:$L$85,$L90)=0,"",SUMIFS(Formulario!$M$28:$M$41,Formulario!$A$28:$A$41,$H90,Formulario!$I$28:$I$41,$I90,Formulario!$J$28:$J$41,$J90,Formulario!$L$28:$L$41,$L90)+SUMIFS(Formulario!$M$58:$M$85,Formulario!$A$58:$A$85,$H90,Formulario!$I$58:$I$85,$I90,Formulario!$J$58:$J$85,$J90,Formulario!$L$58:$L$85,$L90)) | O90: {=IFERROR(INDEX(Formulario!$N$28:$N$85,MATCH(0,COUNTIF($O$88:O89,Formulario!$N$28:$N$85),0)),"")}
H91: =IFERROR(LEFT($O91,SEARCH("|",$O91)-1),"") | I91: =IFERROR(MID($O91,SEARCH("|",$O91)+1,SEARCH("|",$O91,SEARCH("|",$O91)+1)-SEARCH("|",$O91)-1),"") | J91: =IFERROR(MID($O91,SEARCH("|",$O91,SEARCH("|",$O91)+1)+1,SEARCH("|",$O91,SEARCH("|",$O91,SEARCH("|",$O91)+1)+1)-SEARCH("|",$O91,SEARCH("|",$O91)+1)-1),"") | L91: =IFERROR(RIGHT($O91,LEN($O91)-SEARCH("|",$O91,SEARCH("|",$O91,SEARCH("|",$O91)+1)+1)),"") | M91: =+IF(SUMIFS(Formulario!$M$28:$M$41,Formulario!$A$28:$A$41,$H91,Formulario!$I$28:$I$41,$I91,Formulario!$J$28:$J$41,$J91,Formulario!$L$28:$L$41,$L91)+SUMIFS(Formulario!$M$58:$M$85,Formulario!$A$58:$A$85,$H91,Formulario!$I$58:$I$85,$I91,Formulario!$J$58:$J$85,$J91,Formulario!$L$58:$L$85,$L91)=0,"",SUMIFS(Formulario!$M$28:$M$41,Formulario!$A$28:$A$41,$H91,Formulario!$I$28:$I$41,$I91,Formulario!$J$28:$J$41,$J91,Formulario!$L$28:$L$41,$L91)+SUMIFS(Formulario!$M$58:$M$85,Formulario!$A$58:$A$85,$H91,Formulario!$I$58:$I$85,$I91,Formulario!$J$58:$J$85,$J91,Formulario!$L$58:$L$85,$L91)) | O91: {=IFERROR(INDEX(Formulario!$N$28:$N$85,MATCH(0,COUNTIF($O$88:O90,Formulario!$N$28:$N$85),0)),"")}
H92: =IFERROR(LEFT($O92,SEARCH("|",$O92)-1),"") | I92: =IFERROR(MID($O92,SEARCH("|",$O92)+1,SEARCH("|",$O92,SEARCH("|",$O92)+1)-SEARCH("|",$O92)-1),"") | J92: =IFERROR(MID($O92,SEARCH("|",$O92,SEARCH("|",$O92)+1)+1,SEARCH("|",$O92,SEARCH("|",$O92,SEARCH("|",$O92)+1)+1)-SEARCH("|",$O92,SEARCH("|",$O92)+1)-1),"") | L92: =IFERROR(RIGHT($O92,LEN($O92)-SEARCH("|",$O92,SEARCH("|",$O92,SEARCH("|",$O92)+1)+1)),"") | M92: =+IF(SUMIFS(Formulario!$M$28:$M$41,Formulario!$A$28:$A$41,$H92,Formulario!$I$28:$I$41,$I92,Formulario!$J$28:$J$41,$J92,Formulario!$L$28:$L$41,$L92)+SUMIFS(Formulario!$M$58:$M$85,Formulario!$A$58:$A$85,$H92,Formulario!$I$58:$I$85,$I92,Formulario!$J$58:$J$85,$J92,Formulario!$L$58:$L$85,$L92)=0,"",SUMIFS(Formulario!$M$28:$M$41,Formulario!$A$28:$A$41,$H92,Formulario!$I$28:$I$41,$I92,Formulario!$J$28:$J$41,$J92,Formulario!$L$28:$L$41,$L92)+SUMIFS(Formulario!$M$58:$M$85,Formulario!$A$58:$A$85,$H92,Formulario!$I$58:$I$85,$I92,Formulario!$J$58:$J$85,$J92,Formulario!$L$58:$L$85,$L92)) | O92: {=IFERROR(INDEX(Formulario!$N$28:$N$85,MATCH(0,COUNTIF($O$88:O91,Formulario!$N$28:$N$85),0)),"")}
H93: =IFERROR(LEFT($O93,SEARCH("|",$O93)-1),"") | I93: =IFERROR(MID($O93,SEARCH("|",$O93)+1,SEARCH("|",$O93,SEARCH("|",$O93)+1)-SEARCH("|",$O93)-1),"") | J93: =IFERROR(MID($O93,SEARCH("|",$O93,SEARCH("|",$O93)+1)+1,SEARCH("|",$O93,SEARCH("|",$O93,SEARCH("|",$O93)+1)+1)-SEARCH("|",$O93,SEARCH("|",$O93)+1)-1),"") | L93: =IFERROR(RIGHT($O93,LEN($O93)-SEARCH("|",$O93,SEARCH("|",$O93,SEARCH("|",$O93)+1)+1)),"") | M93: =+IF(SUMIFS(Formulario!$M$28:$M$41,Formulario!$A$28:$A$41,$H93,Formulario!$I$28:$I$41,$I93,Formulario!$J$28:$J$41,$J93,Formulario!$L$28:$L$41,$L93)+SUMIFS(Formulario!$M$58:$M$85,Formulario!$A$58:$A$85,$H93,Formulario!$I$58:$I$85,$I93,Formulario!$J$58:$J$85,$J93,Formulario!$L$58:$L$85,$L93)=0,"",SUMIFS(Formulario!$M$28:$M$41,Formulario!$A$28:$A$41,$H93,Formulario!$I$28:$I$41,$I93,Formulario!$J$28:$J$41,$J93,Formulario!$L$28:$L$41,$L93)+SUMIFS(Formulario!$M$58:$M$85,Formulario!$A$58:$A$85,$H93,Formulario!$I$58:$I$85,$I93,Formulario!$J$58:$J$85,$J93,Formulario!$L$58:$L$85,$L93)) | O93: {=IFERROR(INDEX(Formulario!$N$28:$N$85,MATCH(0,COUNTIF($O$88:O92,Formulario!$N$28:$N$85),0)),"")}
H94: =IFERROR(LEFT($O94,SEARCH("|",$O94)-1),"") | I94: =IFERROR(MID($O94,SEARCH("|",$O94)+1,SEARCH("|",$O94,SEARCH("|",$O94)+1)-SEARCH("|",$O94)-1),"") | J94: =IFERROR(MID($O94,SEARCH("|",$O94,SEARCH("|",$O94)+1)+1,SEARCH("|",$O94,SEARCH("|",$O94,SEARCH("|",$O94)+1)+1)-SEARCH("|",$O94,SEARCH("|",$O94)+1)-1),"") | L94: =IFERROR(RIGHT($O94,LEN($O94)-SEARCH("|",$O94,SEARCH("|",$O94,SEARCH("|",$O94)+1)+1)),"") | M94: =+IF(SUMIFS(Formulario!$M$28:$M$41,Formulario!$A$28:$A$41,$H94,Formulario!$I$28:$I$41,$I94,Formulario!$J$28:$J$41,$J94,Formulario!$L$28:$L$41,$L94)+SUMIFS(Formulario!$M$58:$M$85,Formulario!$A$58:$A$85,$H94,Formulario!$I$58:$I$85,$I94,Formulario!$J$58:$J$85,$J94,Formulario!$L$58:$L$85,$L94)=0,"",SUMIFS(Formulario!$M$28:$M$41,Formulario!$A$28:$A$41,$H94,Formulario!$I$28:$I$41,$I94,Formulario!$J$28:$J$41,$J94,Formulario!$L$28:$L$41,$L94)+SUMIFS(Formulario!$M$58:$M$85,Formulario!$A$58:$A$85,$H94,Formulario!$I$58:$I$85,$I94,Formulario!$J$58:$J$85,$J94,Formulario!$L$58:$L$85,$L94)) | O94: {=IFERROR(INDEX(Formulario!$N$28:$N$85,MATCH(0,COUNTIF($O$88:O93,Formulario!$N$28:$N$85),0)),"")}
H95: =IFERROR(LEFT($O95,SEARCH("|",$O95)-1),"") | I95: =IFERROR(MID($O95,SEARCH("|",$O95)+1,SEARCH("|",$O95,SEARCH("|",$O95)+1)-SEARCH("|",$O95)-1),"") | J95: =IFERROR(MID($O95,SEARCH("|",$O95,SEARCH("|",$O95)+1)+1,SEARCH("|",$O95,SEARCH("|",$O95,SEARCH("|",$O95)+1)+1)-SEARCH("|",$O95,SEARCH("|",$O95)+1)-1),"") | L95: =IFERROR(RIGHT($O95,LEN($O95)-SEARCH("|",$O95,SEARCH("|",$O95,SEARCH("|",$O95)+1)+1)),"") | M95: =+IF(SUMIFS(Formulario!$M$28:$M$41,Formulario!$A$28:$A$41,$H95,Formulario!$I$28:$I$41,$I95,Formulario!$J$28:$J$41,$J95,Formulario!$L$28:$L$41,$L95)+SUMIFS(Formulario!$M$58:$M$85,Formulario!$A$58:$A$85,$H95,Formulario!$I$58:$I$85,$I95,Formulario!$J$58:$J$85,$J95,Formulario!$L$58:$L$85,$L95)=0,"",SUMIFS(Formulario!$M$28:$M$41,Formulario!$A$28:$A$41,$H95,Formulario!$I$28:$I$41,$I95,Formulario!$J$28:$J$41,$J95,Formulario!$L$28:$L$41,$L95)+SUMIFS(Formulario!$M$58:$M$85,Formulario!$A$58:$A$85,$H95,Formulario!$I$58:$I$85,$I95,Formulario!$J$58:$J$85,$J95,Formulario!$L$58:$L$85,$L95)) | O95: {=IFERROR(INDEX(Formulario!$N$28:$N$85,MATCH(0,COUNTIF($O$88:O94,Formulario!$N$28:$N$85),0)),"")}
H96: =IFERROR(LEFT($O96,SEARCH("|",$O96)-1),"") | I96: =IFERROR(MID($O96,SEARCH("|",$O96)+1,SEARCH("|",$O96,SEARCH("|",$O96)+1)-SEARCH("|",$O96)-1),"") | J96: =IFERROR(MID($O96,SEARCH("|",$O96,SEARCH("|",$O96)+1)+1,SEARCH("|",$O96,SEARCH("|",$O96,SEARCH("|",$O96)+1)+1)-SEARCH("|",$O96,SEARCH("|",$O96)+1)-1),"") | L96: =IFERROR(RIGHT($O96,LEN($O96)-SEARCH("|",$O96,SEARCH("|",$O96,SEARCH("|",$O96)+1)+1)),"") | M96: =+IF(SUMIFS(Formulario!$M$28:$M$41,Formulario!$A$28:$A$41,$H96,Formulario!$I$28:$I$41,$I96,Formulario!$J$28:$J$41,$J96,Formulario!$L$28:$L$41,$L96)+SUMIFS(Formulario!$M$58:$M$85,Formulario!$A$58:$A$85,$H96,Formulario!$I$58:$I$85,$I96,Formulario!$J$58:$J$85,$J96,Formulario!$L$58:$L$85,$L96)=0,"",SUMIFS(Formulario!$M$28:$M$41,Formulario!$A$28:$A$41,$H96,Formulario!$I$28:$I$41,$I96,Formulario!$J$28:$J$41,$J96,Formulario!$L$28:$L$41,$L96)+SUMIFS(Formulario!$M$58:$M$85,Formulario!$A$58:$A$85,$H96,Formulario!$I$58:$I$85,$I96,Formulario!$J$58:$J$85,$J96,Formulario!$L$58:$L$85,$L96)) | O96: {=IFERROR(INDEX(Formulario!$N$28:$N$85,MATCH(0,COUNTIF($O$88:O95,Formulario!$N$28:$N$85),0)),"")}
H97: =IFERROR(LEFT($O97,SEARCH("|",$O97)-1),"") | I97: =IFERROR(MID($O97,SEARCH("|",$O97)+1,SEARCH("|",$O97,SEARCH("|",$O97)+1)-SEARCH("|",$O97)-1),"") | J97: =IFERROR(MID($O97,SEARCH("|",$O97,SEARCH("|",$O97)+1)+1,SEARCH("|",$O97,SEARCH("|",$O97,SEARCH("|",$O97)+1)+1)-SEARCH("|",$O97,SEARCH("|",$O97)+1)-1),"") | L97: =IFERROR(RIGHT($O97,LEN($O97)-SEARCH("|",$O97,SEARCH("|",$O97,SEARCH("|",$O97)+1)+1)),"") | M97: =+IF(SUMIFS(Formulario!$M$28:$M$41,Formulario!$A$28:$A$41,$H97,Formulario!$I$28:$I$41,$I97,Formulario!$J$28:$J$41,$J97,Formulario!$L$28:$L$41,$L97)+SUMIFS(Formulario!$M$58:$M$85,Formulario!$A$58:$A$85,$H97,Formulario!$I$58:$I$85,$I97,Formulario!$J$58:$J$85,$J97,Formulario!$L$58:$L$85,$L97)=0,"",SUMIFS(Formulario!$M$28:$M$41,Formulario!$A$28:$A$41,$H97,Formulario!$I$28:$I$41,$I97,Formulario!$J$28:$J$41,$J97,Formulario!$L$28:$L$41,$L97)+SUMIFS(Formulario!$M$58:$M$85,Formulario!$A$58:$A$85,$H97,Formulario!$I$58:$I$85,$I97,Formulario!$J$58:$J$85,$J97,Formulario!$L$58:$L$85,$L97)) | O97: {=IFERROR(INDEX(Formulario!$N$28:$N$85,MATCH(0,COUNTIF($O$88:O96,Formulario!$N$28:$N$85),0)),"")}
H98: =IFERROR(LEFT($O98,SEARCH("|",$O98)-1),"") | I98: =IFERROR(MID($O98,SEARCH("|",$O98)+1,SEARCH("|",$O98,SEARCH("|",$O98)+1)-SEARCH("|",$O98)-1),"") | J98: =IFERROR(MID($O98,SEARCH("|",$O98,SEARCH("|",$O98)+1)+1,SEARCH("|",$O98,SEARCH("|",$O98,SEARCH("|",$O98)+1)+1)-SEARCH("|",$O98,SEARCH("|",$O98)+1)-1),"") | L98: =IFERROR(RIGHT($O98,LEN($O98)-SEARCH("|",$O98,SEARCH("|",$O98,SEARCH("|",$O98)+1)+1)),"") | M98: =+IF(SUMIFS(Formulario!$M$28:$M$41,Formulario!$A$28:$A$41,$H98,Formulario!$I$28:$I$41,$I98,Formulario!$J$28:$J$41,$J98,Formulario!$L$28:$L$41,$L98)+SUMIFS(Formulario!$M$58:$M$85,Formulario!$A$58:$A$85,$H98,Formulario!$I$58:$I$85,$I98,Formulario!$J$58:$J$85,$J98,Formulario!$L$58:$L$85,$L98)=0,"",SUMIFS(Formulario!$M$28:$M$41,Formulario!$A$28:$A$41,$H98,Formulario!$I$28:$I$41,$I98,Formulario!$J$28:$J$41,$J98,Formulario!$L$28:$L$41,$L98)+SUMIFS(Formulario!$M$58:$M$85,Formulario!$A$58:$A$85,$H98,Formulario!$I$58:$I$85,$I98,Formulario!$J$58:$J$85,$J98,Formulario!$L$58:$L$85,$L98)) | O98: {=IFERROR(INDEX(Formulario!$N$28:$N$85,MATCH(0,COUNTIF($O$88:O97,Formulario!$N$28:$N$85),0)),"")}
H99: =IFERROR(LEFT($O99,SEARCH("|",$O99)-1),"") | I99: =IFERROR(MID($O99,SEARCH("|",$O99)+1,SEARCH("|",$O99,SEARCH("|",$O99)+1)-SEARCH("|",$O99)-1),"") | J99: =IFERROR(MID($O99,SEARCH("|",$O99,SEARCH("|",$O99)+1)+1,SEARCH("|",$O99,SEARCH("|",$O99,SEARCH("|",$O99)+1)+1)-SEARCH("|",$O99,SEARCH("|",$O99)+1)-1),"") | L99: =IFERROR(RIGHT($O99,LEN($O99)-SEARCH("|",$O99,SEARCH("|",$O99,SEARCH("|",$O99)+1)+1)),"") | M99: =+IF(SUMIFS(Formulario!$M$28:$M$41,Formulario!$A$28:$A$41,$H99,Formulario!$I$28:$I$41,$I99,Formulario!$J$28:$J$41,$J99,Formulario!$L$28:$L$41,$L99)+SUMIFS(Formulario!$M$58:$M$85,Formulario!$A$58:$A$85,$H99,Formulario!$I$58:$I$85,$I99,Formulario!$J$58:$J$85,$J99,Formulario!$L$58:$L$85,$L99)=0,"",SUMIFS(Formulario!$M$28:$M$41,Formulario!$A$28:$A$41,$H99,Formulario!$I$28:$I$41,$I99,Formulario!$J$28:$J$41,$J99,Formulario!$L$28:$L$41,$L99)+SUMIFS(Formulario!$M$58:$M$85,Formulario!$A$58:$A$85,$H99,Formulario!$I$58:$I$85,$I99,Formulario!$J$58:$J$85,$J99,Formulario!$L$58:$L$85,$L99)) | O99: {=IFERROR(INDEX(Formulario!$N$28:$N$85,MATCH(0,COUNTIF($O$88:O98,Formulario!$N$28:$N$85),0)),"")}
H101: Total | M101: =SUM(M89:M100)
J102: Facturas | L102: =SUMIF($A$58:$A$101,"Factura",$L$58:$M$101)
J103: Boletas | L103: =SUMIF($A$58:$A$101,"Boleta",$L$58:$M$101)
